pydbmanager/__init__.py
pydbmanager/config.py
pydbmanager/connection.py
pydbmanager/operations.py
pydbmanager/utils.py
pydbmanager-0.1.7.dist-info/licenses/LICENSE
pydbmanager-0.1.7.dist-info/METADATA
pydbmanager-0.1.7.dist-info/WHEEL
pydbmanager-0.1.7.dist-info/top_level.txt
pydbmanager-0.1.7.dist-info/RECORD
