Metadata-Version: 2.4
Name: pydbmanager
Version: 0.1.7
Summary: A Python package for seamless SQL Server database management, supporting secure connections, query execution, batch fetching, caching, and result exporting.
Home-page: https://github.com/rohit180497/PyDBManager
Author: Rohit Kosamkar
Author-email: rohitkosamkar97@gmail.com
Project-URL: Bug Tracker, https://github.com/rohit180497/PyDBManager/issues
Project-URL: Documentation, https://github.com/rohit180497/PyDBManager#readme
Project-URL: Source Code, https://github.com/rohit180497/PyDBManager
Keywords: SQL Server,database management,pyodbc,Python,SQL
Classifier: Development Status :: 4 - Beta
Classifier: Intended Audience :: Developers
Classifier: Topic :: Database :: Database Engines/Servers
Classifier: Programming Language :: Python :: 3
Classifier: Programming Language :: Python :: 3.8
Classifier: Programming Language :: Python :: 3.9
Classifier: Programming Language :: Python :: 3.10
Classifier: License :: OSI Approved :: MIT License
Classifier: Operating System :: OS Independent
Requires-Python: >=3.8
License-File: LICENSE
Requires-Dist: pyodbc>=4.0.32
Requires-Dist: pandas>=1.3.0
Requires-Dist: python-dotenv>=0.21.0
Requires-Dist: sqlalchemy>=1.4.0
Dynamic: author
Dynamic: author-email
Dynamic: classifier
Dynamic: description
Dynamic: description-content-type
Dynamic: home-page
Dynamic: keywords
Dynamic: license-file
Dynamic: project-url
Dynamic: requires-dist
Dynamic: requires-python
Dynamic: summary
